Workbook

Sheet README
B2: Mumbai Buddies — Financial Model
B3: Operating cost + pricing model. Built May 2026. All amounts INR.
B6: THE PROBLEM THIS MODEL FIXES
B7: The locked pricing model nets only ~₹285 per booking — a ~3.5% effective take rate.
B8: The platform processes the full ~₹6,600 booking through Razorpay (paying ~4% on all of
B9: it) but takes margin only on the ₹2,200 buddy fee. Payment fees eat ~half of gross
B10: revenue. The transit-tourism research report flagged this as structurally unprofitable
B11: at every scale. No marketplace survives at a 3.5% take rate — OTAs run 15–25%.
B13: THE FIX — "ALL OF THE ABOVE" BLENDED PRICING
B14: Three levers stacked, each kept moderate so the total price stays competitive:
B15: 1. Platform margin on the buddy fee (default 12%) — replaces the hidden 12.5/12.5 split
B16: 2. Platform margin on the itinerary fund (default 8%) — it is no longer pure pass-through
... B41: unlock, it just is not a magic wand.

Sheet Assumptions
A1: Assumptions — adjust the blue cells
A3: PRICING LEVERS
A4: Buddy fee — base (₹) | B4: 2200 | G4: What the buddy is quoted before platform margin
A5: Platform margin on buddy fee | B5: 0.12 | G5: Lever 1 — replaces the old hidden 12.5/12.5 split
A6: Itinerary fund — base (₹) | B6: 2800 | G6: Agreed day's expenses (food+transport+entries, both people)
A7: Platform margin on itinerary fund | B7: 0.08 | G7: Lever 2 — itinerary fund is no longer pure pass-through
A8: Buffer rate (% of itinerary fund) | B8: 0.2 | G8: Refundable cushion; no platform margin taken on it
A9: Service & Safety fee | B9: 0.11 | G9: Lever 3 — visible fee on (buddy fee + itinerary fund)
A10: GST rate | B10: 0.05 | G10: Tour Operator HSN 9985, no ITC
A11: Deposit per side (₹) | B11: 500 | G11: Refundable; held in escrow, not revenue
A12: Razorpay blended fee | B12: 0.04 | G12: Intl card MDR + FX markup on the full collected amount
A13: TDS rate — Sec 194C | B13: 0.01 | G13: Withheld from buddy fee payout
A14: Deposit forfeit rate | B14: 0.07 | G14: Share of bookings where a deposit is forfeited
A15: Avg forfeit revenue per forfeit (₹) | B15: 750 | G15: Blended across traveler-deposit + late-fee forfeits
... A17: Social security levy (% of buddy payout) | B17: 0.015 | G17: Code on Social Security 2020 aggregator contribution
A19: BOOKING VOLUME (bookings per year)
A20: Scenario | B20: Year 1 | C20: Year 2 | D20: Year 3 | E20: Year 4 | F20: Year 5
A21: Base case | B21: 1000 | C21: 4500 | D21: 12000 | E21: 30000 | F21: 54000
A22: Conservative | B22: 300 | C22: 1200 | D22: 3000 | E22: 6500 | F22: 10800
A23: Optimistic | B23: 2000 | C23: 9000 | D23: 25000 | E23: 60000 | F23: 108000
A25: Volume path is the founder/analyst estimate from the transit-tourism research report (May 2026).

Sheet Unit Economics
A1: Unit Economics — per booking
B3: Old model (locked) | C3: New model (blended) | D3: Notes
A5: INPUTS
A6: Buddy fee — base (₹) | B6: =Assumptions!B4 -> 2200 | C6: =Assumptions!B4 -> 2200 | D6: Same base both models — only the architecture differs
A7: Itinerary fund — base (₹) | B7: =Assumptions!B6 -> 2800 | C7: =Assumptions!B6 -> 2800
A9: TRAVELER-FACING CHARGES
A10: Buddy fee (as shown to traveler) | B10: =B6*1.125 -> 2475 | C10: =C6*(1+Assumptions!B5) -> 2464 | D10: Old: hidden +12.5%. New: + platform margin
A11: Itinerary fund (as shown to traveler) | B11: =B7 -> 2800 | C11: =C7*(1+Assumptions!B7) -> 3024 | D11: Old: pure pass-through. New: + platform margin
A12: Buffer | B12: =B7*Assumptions!B8 -> 560 | C12: =C7*Assumptions!B8 -> 560 | D12: 20% of itinerary fund, refundable
A13: Service & Safety fee | B13: 0 | C13: =(C6+C7)*Assumptions!B9 -> 550 | D13: New model only — the visible fee
A14: Subtotal (pre-GST) | B14: =SUM(B10:B13) -> 5835 | C14: =SUM(C10:C13) -> 6598
A15: GST | B15: =B14*Assumptions!B10 -> 291.75 | C15: =C14*Assumptions!B10 -> 329.9
A16: Refundable deposit | B16: =Assumptions!B11 -> 500 | C16: =Assumptions!B11 -> 500 | D16: Held in escrow; returned after trip
A17: TRAVELER TOTAL | B17: =B14+B15+B16 -> 6626.75 | C17: =C14+C15+C16 -> 7427.9 | D17: What the traveler pays
A19: PLATFORM REVENUE
A20: Margin from buddy fee | B20: =B6*0.25 -> 550 | C20: =C6*Assumptions!B5 -> 264 | D20: Old: 25% of buddy fee. New: platform margin %
A21: Margin from itinerary fund | B21: 0 | C21: =C7*Assumptions!B7 -> 224 | D21: New model only
A22: Service & Safety fee | B22: 0 | C22: =C13 -> 550 | D22: New model only
A23: Platform gross revenue | B23: =SUM(B20:B22) -> 550 | C23: =SUM(C20:C22) -> 1038
A24: Less: Razorpay fees | B24: =-B17*Assumptions!B12 -> -265.07 | C24: =-C17*Assumptions!B12 -> -297.116 | D24: ~4% on the full collected amount
A25: PLATFORM NET CONTRIBUTION | B25: =B23+B24 -> 284.93 | C25: =C23+C24 -> 740.884 | D25: Per-booking margin to the platform
A27: BUDDY ECONOMICS
A28: Buddy fee received (post-fee, post-TDS) | B28: =B6*0.875 -> 1925 | C28: =C6*(1-Assumptions!B13) -> 2178 | D28: Old: -12.5%. New: clean fee minus 1% TDS
A29: Itinerary fund entrusted to buddy | B29: =B7 -> 2800 | C29: =C7 -> 2800 | D29: Spent on the day; not buddy income
A30: Deposit posted then returned | B30: =Assumptions!B11 -> 500 | C30: =Assumptions!B11 -> 500
A32: KEY METRICS
A33: GMV per booking (excl. deposit) | B33: =B14+B15 -> 6126.75 | C33: =C14+C15 -> 6927.9 | D33: Subtotal + GST
A34: Effective gross take rate | B34: =B23/B17 -> 0.082996944 | C34: =C23/C17 -> 0.1397434 | D34: Platform gross / traveler total
A35: Effective net take rate | B35: =B25/B17 -> 0.042996944 | C35: =C25/C17 -> 0.0997434 | D35: Platform net / traveler total
A36: Net contribution per booking (₹) | B36: =B25 -> 284.93 | C36: =C25 -> 740.884
A37: New model improvement vs old | C37: =C25/B25-1 -> 1.6002316 | D37: How much more the platform nets per booking under the new pricing

Sheet Operating Costs
A1: Operating Costs — 5-year (₹ Lakh)
A2: 1 Lakh = ₹100,000. Blue cells are inputs; change them to re-plan.
A4: BOOTSTRAPPED — founder keeps the day job, lean organic marketing
A5: Cost line | B5: Year 1 | C5: Year 2 | D5: Year 3 | E5: Year 4 | F5: Year 5
A6: Tech infrastructure | B6: 2.4 | C6: 4.8 | D6: 8.4 | E6: 14.4 | F6: 24 | G6: Supabase, Vercel, Cloudinary, Razorpay infra
A7: Background verification | B7: 1.3 | C7: 3 | D7: 6 | E7: 12 | F7: 20 | G7: ~₹500/buddy check, IDfy/Signzy
A8: Insurance | B8: 1.2 | C8: 1.7 | D8: 2.8 | E8: 5.5 | F8: 9.1 | G8: Professional Indemnity + Cyber + Group PA
A9: Customer support | B9: 0 | C9: 6 | D9: 14.4 | E9: 19.2 | F9: 24 | G9: Founder does it Y1; FTEs added from Y2
A10: Marketing / CAC | B10: 4 | C10: 12 | D10: 24 | E10: 40 | F10: 60 | G10: Organic-first — VJTI network, content, SEO
A11: Compliance (CA / ROC / audit / legal) | B11: 3 | C11: 4.5 | D11: 6 | E11: 8 | F11: 10 | G11: CA retainer + annual filings
A12: Founder / team salaries | B12: 0 | C12: 12 | D12: 36 | E12: 72 | F12: 120 | G12: ₹0 in Y1 — founder keeps Rekise Marine job
A13: Misc / one-time | B13: 2 | C13: 3 | D13: 4 | E13: 6 | F13: 8 | G13: Incorporation, trademark, contingency
A14: Aggregator social security levy | B14: =Assumptions!B21*Assumptions!B4*Assumptions!B17/100000 -> 0.33 | C14: =Assumptions!C21*Assumptions!B4*Assumptions!B17/100000 -> 1.485 | D14: =Assumptions!D21*Assumptions!B4*Assumptions!B17/100000 -> 3.96 | E14: =Assumptions!E21*Assumptions!B4*Assumptions!B17/100000 -> 9.9 | F14: =Assumptions!F21*Assumptions!B4*Assumptions!B17/100000 -> 17.82 | G14: 1.5% of buddy-fee payouts — Code on Social Security 2020
A15: TOTAL — Bootstrapped | B15: =SUM(B6:B14) -> 14.23 | C15: =SUM(C6:C14) -> 48.485 | D15: =SUM(D6:D14) -> 105.56 | E15: =SUM(E6:E14) -> 187 | F15: =SUM(F6:F14) -> 292.92
A17: FUNDED — full salaries, paid marketing burn (the research report's model)
A18: Cost line | B18: Year 1 | C18: Year 2 | D18: Year 3 | E18: Year 4 | F18: Year 5
A19: Tech infrastructure | B19: 2.4 | C19: 4.8 | D19: 8.4 | E19: 14.4 | F19: 24
A20: Background verification | B20: 1.3 | C20: 4 | D20: 8 | E20: 15 | F20: 25
A21: Insurance | B21: 1.2 | C21: 1.7 | D21: 2.8 | E21: 5.5 | F21: 9.1
A22: Customer support | B22: 4.8 | C22: 9.6 | D22: 14.4 | E22: 19.2 | F22: 24 | G22: 1 FTE Y1 → 4 FTE Y5
A23: Marketing / CAC | B23: 25 | C23: 36 | D23: 48 | E23: 60 | F23: 72 | G23: Burn-pricing to buy growth
A24: Compliance (CA / ROC / audit / legal) | B24: 3 | C24: 4.5 | D24: 6 | E24: 8 | F24: 10
A25: Founder / team salaries | B25: 30 | C25: 60 | D25: 100 | E25: 150 | F25: 220 | G25: Market-rate from Y1
A26: Misc / one-time | B26: 5 | C26: 5 | D26: 7.5 | E26: 10 | F26: 15
A27: Aggregator social security levy | B27: =Assumptions!B21*Assumptions!B4*Assumptions!B17/100000 -> 0.33 | C27: =Assumptions!C21*Assumptions!B4*Assumptions!B17/100000 -> 1.485 | D27: =Assumptions!D21*Assumptions!B4*Assumptions!B17/100000 -> 3.96 | E27: =Assumptions!E21*Assumptions!B4*Assumptions!B17/100000 -> 9.9 | F27: =Assumptions!F21*Assumptions!B4*Assumptions!B17/100000 -> 17.82
A28: TOTAL — Funded | B28: =SUM(B19:B27) -> 73.03 | C28: =SUM(C19:C27) -> 127.085 | D28: =SUM(D19:D27) -> 199.06 | E28: =SUM(E19:E27) -> 292 | F28: =SUM(F19:F27) -> 416.92

Sheet 5-Year P&L
A1: 5-Year P&L — base-case volume (₹ Lakh)
A2: Per-booking economics from the New model. Change levers on Assumptions / Operating Costs.
A4: BOOTSTRAPPED SCENARIO
A5: Line | B5: Year 1 | C5: Year 2 | D5: Year 3 | E5: Year 4 | F5: Year 5
A6: Bookings (#) | B6: =Assumptions!B21 -> 1000 | C6: =Assumptions!C21 -> 4500 | D6: =Assumptions!D21 -> 12000 | E6: =Assumptions!E21 -> 30000 | F6: =Assumptions!F21 -> 54000
A7: GMV (₹ Lakh) | B7: =B6*'Unit Economics'!C33/100000 -> 69.279 | C7: =C6*'Unit Economics'!C33/100000 -> 311.7555 | D7: =D6*'Unit Economics'!C33/100000 -> 831.348 | E7: =E6*'Unit Economics'!C33/100000 -> 2078.37 | F7: =F6*'Unit Economics'!C33/100000 -> 3741.066
A8: Platform net contribution (₹ Lakh) | B8: =B6*'Unit Economics'!C25/100000 -> 7.40884 | C8: =C6*'Unit Economics'!C25/100000 -> 33.33978 | D8: =D6*'Unit Economics'!C25/100000 -> 88.90608 | E8: =E6*'Unit Economics'!C25/100000 -> 222.2652 | F8: =F6*'Unit Economics'!C25/100000 -> 400.07736
A9: Deposit-forfeit revenue (₹ Lakh) | B9: =B6*Assumptions!B14*Assumptions!B15/100000 -> 0.525 | C9: =C6*Assumptions!B14*Assumptions!B15/100000 -> 2.3625 | D9: =D6*Assumptions!B14*Assumptions!B15/100000 -> 6.3 | E9: =E6*Assumptions!B14*Assumptions!B15/100000 -> 15.75 | F9: =F6*Assumptions!B14*Assumptions!B15/100000 -> 28.35
A10: Net revenue (₹ Lakh) | B10: =B8+B9 -> 7.93384 | C10: =C8+C9 -> 35.70228 | D10: =D8+D9 -> 95.20608 | E10: =E8+E9 -> 238.0152 | F10: =F8+F9 -> 428.42736
A11: Less: COGS (refunds / variable support) | B11: =-B10*Assumptions!B16 -> -1.586768 | C11: =-C10*Assumptions!B16 -> -7.140456 | D11: =-D10*Assumptions!B16 -> -19.041216 | E11: =-E10*Assumptions!B16 -> -47.60304 | F11: =-F10*Assumptions!B16 -> -85.685472
A12: Gross margin (₹ Lakh) | B12: =B10+B11 -> 6.347072 | C12: =C10+C11 -> 28.561824 | D12: =D10+D11 -> 76.164864 | E12: =E10+E11 -> 190.41216 | F12: =F10+F11 -> 342.74189
A13: Less: Operating costs (₹ Lakh) | B13: =-'Operating Costs'!B15 -> -14.23 | C13: =-'Operating Costs'!C15 -> -48.485 | D13: =-'Operating Costs'!D15 -> -105.56 | E13: =-'Operating Costs'!E15 -> -187 | F13: =-'Operating Costs'!F15 -> -292.92
A14: EBITDA (₹ Lakh) | B14: =B12+B13 -> -7.882928 | C14: =C12+C13 -> -19.923176 | D14: =D12+D13 -> -29.395136 | E14: =E12+E13 -> 3.41216 | F14: =F12+F13 -> 49.821888
A15: EBITDA margin (% of GMV) | B15: =B14/B7 -> -0.11378525 | C15: =C14/C7 -> -0.063906414 | D15: =D14/D7 -> -0.035358401 | E15: =E14/E7 -> 0.0016417481 | F15: =F14/F7 -> 0.013317565
A16: Cumulative EBITDA (₹ Lakh) | B16: =B14 -> -7.882928 | C16: =B16+C14 -> -27.806104 | D16: =C16+D14 -> -57.20124 | E16: =D16+E14 -> -53.78908 | F16: =E16+F14 -> -3.967192
A20: FUNDED SCENARIO
A21: Line | B21: Year 1 | C21: Year 2 | D21: Year 3 | E21: Year 4 | F21: Year 5
A22: Bookings (#) | B22: =Assumptions!B21 -> 1000 | C22: =Assumptions!C21 -> 4500 | D22: =Assumptions!D21 -> 12000 | E22: =Assumptions!E21 -> 30000 | F22: =Assumptions!F21 -> 54000
A23: GMV (₹ Lakh) | B23: =B22*'Unit Economics'!C33/100000 -> 69.279 | C23: =C22*'Unit Economics'!C33/100000 -> 311.7555 | D23: =D22*'Unit Economics'!C33/100000 -> 831.348 | E23: =E22*'Unit Economics'!C33/100000 -> 2078.37 | F23: =F22*'Unit Economics'!C33/100000 -> 3741.066
A24: Platform net contribution (₹ Lakh) | B24: =B22*'Unit Economics'!C25/100000 -> 7.40884 | C24: =C22*'Unit Economics'!C25/100000 -> 33.33978 | D24: =D22*'Unit Economics'!C25/100000 -> 88.90608 | E24: =E22*'Unit Economics'!C25/100000 -> 222.2652 | F24: =F22*'Unit Economics'!C25/100000 -> 400.07736
A25: Deposit-forfeit revenue (₹ Lakh) | B25: =B22*Assumptions!B14*Assumptions!B15/100000 -> 0.525 | C25: =C22*Assumptions!B14*Assumptions!B15/100000 -> 2.3625 | D25: =D22*Assumptions!B14*Assumptions!B15/100000 -> 6.3 | E25: =E22*Assumptions!B14*Assumptions!B15/100000 -> 15.75 | F25: =F22*Assumptions!B14*Assumptions!B15/100000 -> 28.35
A26: Net revenue (₹ Lakh) | B26: =B24+B25 -> 7.93384 | C26: =C24+C25 -> 35.70228 | D26: =D24+D25 -> 95.20608 | E26: =E24+E25 -> 238.0152 | F26: =F24+F25 -> 428.42736
A27: Less: COGS (refunds / variable support) | B27: =-B26*Assumptions!B16 -> -1.586768 | C27: =-C26*Assumptions!B16 -> -7.140456 | D27: =-D26*Assumptions!B16 -> -19.041216 | E27: =-E26*Assumptions!B16 -> -47.60304 | F27: =-F26*Assumptions!B16 -> -85.685472
A28: Gross margin (₹ Lakh) | B28: =B26+B27 -> 6.347072 | C28: =C26+C27 -> 28.561824 | D28: =D26+D27 -> 76.164864 | E28: =E26+E27 -> 190.41216 | F28: =F26+F27 -> 342.74189
A29: Less: Operating costs (₹ Lakh) | B29: =-'Operating Costs'!B28 -> -73.03 | C29: =-'Operating Costs'!C28 -> -127.085 | D29: =-'Operating Costs'!D28 -> -199.06 | E29: =-'Operating Costs'!E28 -> -292 | F29: =-'Operating Costs'!F28 -> -416.92
A30: EBITDA (₹ Lakh) | B30: =B28+B29 -> -66.682928 | C30: =C28+C29 -> -98.523176 | D30: =D28+D29 -> -122.89514 | E30: =E28+E29 -> -101.58784 | F30: =F28+F29 -> -74.178112
A31: EBITDA margin (% of GMV) | B31: =B30/B23 -> -0.96252729 | C31: =C30/C23 -> -0.31602707 | D31: =D30/D23 -> -0.14782634 | E31: =E30/E23 -> -0.048878612 | F31: =F30/F23 -> -0.019828068
A32: Cumulative EBITDA (₹ Lakh) | B32: =B30 -> -66.682928 | C32: =B32+C30 -> -165.2061 | D32: =C32+D30 -> -288.10124 | E32: =D32+E30 -> -389.68908 | F32: =E32+F30 -> -463.86719
A36: Read: at the default opex, bootstrapped turns EBITDA-positive in Year 4; funded is still burning at Year 5.
A37: Hold founder/team salary down longer and breakeven moves earlier. At the old ~₹285/booking, neither ever turns positive.

Sheet Scenarios
A1: Scenario summary — Year 5 (₹ Lakh, bootstrapped opex)
A2: Volume paths from Assumptions. Year-5 economics under the bootstrapped cost base.
A4: YEAR-5 OUTCOMES BY VOLUME SCENARIO
A5: Metric | B5: Conservative | C5: Base | D5: Optimistic | E5: Notes
A6: Year-5 bookings (#) | B6: =Assumptions!F22 -> 10800 | C6: =Assumptions!F21 -> 54000 | D6: =Assumptions!F23 -> 108000 | E6: 1% / 5% / 10% of Year-5 SAM per the research report
A7: Year-5 GMV (₹ Lakh) | B7: =B6*'Unit Economics'!C33/100000 -> 748.2132 | C7: =C6*'Unit Economics'!C33/100000 -> 3741.066 | D7: =D6*'Unit Economics'!C33/100000 -> 7482.132 | E7: Bookings x GMV/booking
A8: Year-5 net revenue (₹ Lakh) | B8: =B6*('Unit Economics'!C25 + Assumptions!B14*Assumptions!B15)/100000 -> 85.685472 | C8: =C6*('Unit Economics'!C25 + Assumptions!B14*Assumptions!B15)/100000 -> 428.42736 | D8: =D6*('Unit Economics'!C25 + Assumptions!B14*Assumptions!B15)/100000 -> 856.85472 | E8: Platform contribution + deposit-forfeit revenue
A9: Year-5 gross margin (₹ Lakh) | B9: =B8*(1-Assumptions!B16) -> 68.548378 | C9: =C8*(1-Assumptions!B16) -> 342.74189 | D9: =D8*(1-Assumptions!B16) -> 685.48378
A10: Year-5 operating costs (₹ Lakh) | B10: ='Operating Costs'!F15 -> 292.92 | C10: ='Operating Costs'!F15 -> 292.92 | D10: ='Operating Costs'!F15 -> 292.92 | E10: Bootstrapped Year-5 total (same cost base across scenarios)
A11: Year-5 EBITDA (₹ Lakh) | B11: =B9-B10 -> -224.37162 | C11: =C9-C10 -> 49.821888 | D11: =D9-D10 -> 392.56378
A12: Year-5 EBITDA margin (% of GMV) | B12: =B11/B7 -> -0.29987659 | C12: =C11/C7 -> 0.013317565 | D12: =D11/D7 -> 0.052466834
A14: WHAT THIS TELLS YOU
A15: Conservative — a real side business. Covers costs, modest surplus, no need to raise.
A16: Base — a fundable small business. Year-5 EBITDA positive on the bootstrapped cost base.
A17: Optimistic — acquisition-attractive. The research report flags Adani / MakeMyTrip / Klook as buyers.
A19: The single biggest lever is the take rate, not the volume. Fixing pricing moves every column.
A20: Second biggest is founder salary timing — staying lean through Year 2 is what bridges to profit.
